_hamming_codec.pypy37-pp73-darwin.so
cli/__init__.py
cli/cli.py
cli/codec_cli.py
hamming_codec/__init__.py
hamming_codec/_hamming_codec.pypy37-pp73-darwin.so
hamming_codec-0.3.5.data/data/CMakeLists.txt
hamming_codec-0.3.5.data/data/LICENSE
hamming_codec-0.3.5.data/data/README.md
hamming_codec-0.3.5.data/data/pyproject.toml
hamming_codec-0.3.5.data/data/requirements.txt
hamming_codec-0.3.5.data/data/exts/pybind11/CMakeLists.txt
hamming_codec-0.3.5.data/data/exts/pybind11/LICENSE
hamming_codec-0.3.5.data/data/exts/pybind11/include/pybind11/attr.h
hamming_codec-0.3.5.data/data/exts/pybind11/include/pybind11/buffer_info.h
hamming_codec-0.3.5.data/data/exts/pybind11/include/pybind11/cast.h
hamming_codec-0.3.5.data/data/exts/pybind11/include/pybind11/chrono.h
hamming_codec-0.3.5.data/data/exts/pybind11/include/pybind11/common.h
hamming_codec-0.3.5.data/data/exts/pybind11/include/pybind11/complex.h
hamming_codec-0.3.5.data/data/exts/pybind11/include/pybind11/eigen.h
hamming_codec-0.3.5.data/data/exts/pybind11/include/pybind11/embed.h
hamming_codec-0.3.5.data/data/exts/pybind11/include/pybind11/eval.h
hamming_codec-0.3.5.data/data/exts/pybind11/include/pybind11/functional.h
hamming_codec-0.3.5.data/data/exts/pybind11/include/pybind11/iostream.h
hamming_codec-0.3.5.data/data/exts/pybind11/include/pybind11/numpy.h
hamming_codec-0.3.5.data/data/exts/pybind11/include/pybind11/operators.h
hamming_codec-0.3.5.data/data/exts/pybind11/include/pybind11/options.h
hamming_codec-0.3.5.data/data/exts/pybind11/include/pybind11/pybind11.h
hamming_codec-0.3.5.data/data/exts/pybind11/include/pybind11/pytypes.h
hamming_codec-0.3.5.data/data/exts/pybind11/include/pybind11/stl.h
hamming_codec-0.3.5.data/data/exts/pybind11/include/pybind11/stl_bind.h
hamming_codec-0.3.5.data/data/exts/pybind11/include/pybind11/detail/class.h
hamming_codec-0.3.5.data/data/exts/pybind11/include/pybind11/detail/common.h
hamming_codec-0.3.5.data/data/exts/pybind11/include/pybind11/detail/descr.h
hamming_codec-0.3.5.dist-info/LICENSE
hamming_codec-0.3.5.dist-info/METADATA
hamming_codec-0.3.5.dist-info/WHEEL
hamming_codec-0.3.5.dist-info/entry_points.txt
hamming_codec-0.3.5.dist-info/top_level.txt
hamming_codec-0.3.5.dist-info/RECORD
