Metadata-Version: 2.1
Name: hamming_codec
Version: 0.3.5
Summary: Simple encode/decode utilities for bit-error correcting Hamming codes
Home-page: https://github.com/dantrim/hamming-codec
Author: Daniel Joseph Antrim
Author-email: dantrim1023@gmail.com
License: MIT
Platform: UNKNOWN
Classifier: License :: OSI Approved :: MIT License
Classifier: Programming Language :: Python :: 3
Classifier: Programming Language :: Python :: 3.8
License-File: LICENSE
